lawfactory_utils/__index__.py
lawfactory_utils/__version.py
lawfactory_utils/urls.py
lawfactory_utils-0.2.2.data/scripts/lawfactory_where_is_my_cache
lawfactory_utils-0.2.2.dist-info/LICENSE
lawfactory_utils-0.2.2.dist-info/METADATA
lawfactory_utils-0.2.2.dist-info/WHEEL
lawfactory_utils-0.2.2.dist-info/top_level.txt
lawfactory_utils-0.2.2.dist-info/RECORD
