Metadata-Version: 2.1
Name: lawfactory-utils
Version: 0.2.2
Summary: Python utils for The Law Factory parsers
Home-page: https://github.com/regardscitoyens/lawfactory_utils
Author: Regards Citoyens
Author-email: contact@regardscitoyens.org
License: MIT
Keywords: scraping politics data
Platform: UNKNOWN
Classifier: Development Status :: 1 - Planning
Classifier: License :: OSI Approved :: MIT License
Classifier: Operating System :: OS Independent
Classifier: Programming Language :: Python :: 3
Requires-Dist: requests (<2.21,>=2.20)
Requires-Dist: lxml (<4.3,>=4.2)
Requires-Dist: beautifulsoup4 (<4.7,>=4.6)
